{
	"name": "DelimitedText1",
	"properties": {
		"linkedServiceName": {
			"referenceName": "AzureDataLakeStorage1",
			"type": "LinkedServiceReference"
		},
		"annotations": [],
		"type": "DelimitedText",
		"typeProperties": {
			"location": {
				"type": "AzureBlobFSLocation",
				"fileSystem": "somadfscontainer"
			},
			"columnDelimiter": ",",
			"escapeChar": "\\",
			"firstRowAsHeader": true,
			"quoteChar": "\""
		},
		"schema": [
			{
				"name": "1",
				"type": "String"
			},
			{
				"name": "(+)-inotropic",
				"type": "String"
			},
			{
				"name": "An agent that alters the force or energy of muscular contractions. Positively inotropic agents increase the strength of muscular contraction.",
				"type": "String"
			},
			{
				"name": "NULL",
				"type": "String"
			}
		]
	},
	"type": "Microsoft.DataFactory/factories/datasets"
}